{
  "teamName": "Bournemouth",
  "matches": [
    {
      "date": "2025-12-20",
      "opponent": "Burnley",
      "isHome": true,
      "goalsFor": 1,
      "goalsAgainst": 1,
      "result": "D"
    },
    {
      "date": "2025-12-15",
      "opponent": "Manchester United",
      "isHome": false,
      "goalsFor": 4,
      "goalsAgainst": 4,
      "result": "D"
    },
    {
      "date": "2025-12-06",
      "opponent": "Chelsea",
      "isHome": true,
      "goalsFor": 0,
      "goalsAgainst": 0,
      "result": "D"
    },
    {
      "date": "2025-12-02",
      "opponent": "Everton",
      "isHome": true,
      "goalsFor": 0,
      "goalsAgainst": 1,
      "result": "L"
    },
    {
      "date": "2025-11-29",
      "opponent": "Sunderland",
      "isHome": false,
      "goalsFor": 2,
      "goalsAgainst": 3,
      "result": "L"
    },
    {
      "date": "2025-11-22",
      "opponent": "West Ham",
      "isHome": true,
      "goalsFor": 2,
      "goalsAgainst": 2,
      "result": "D"
    },
    {
      "date": "2025-11-09",
      "opponent": "Aston Villa",
      "isHome": false,
      "goalsFor": 0,
      "goalsAgainst": 4,
      "result": "L"
    },
    {
      "date": "2025-11-02",
      "opponent": "Manchester City",
      "isHome": false,
      "goalsFor": 1,
      "goalsAgainst": 3,
      "result": "L"
    },
    {
      "date": "2025-10-26",
      "opponent": "Nottingham Forest",
      "isHome": true,
      "goalsFor": 2,
      "goalsAgainst": 0,
      "result": "W"
    },
    {
      "date": "2025-10-18",
      "opponent": "Crystal Palace",
      "isHome": false,
      "goalsFor": 3,
      "goalsAgainst": 3,
      "result": "D"
    },
    {
      "date": "2025-10-03",
      "opponent": "Fulham",
      "isHome": true,
      "goalsFor": 3,
      "goalsAgainst": 1,
      "result": "W"
    },
    {
      "date": "2025-09-27",
      "opponent": "Leeds United",
      "isHome": false,
      "goalsFor": 2,
      "goalsAgainst": 2,
      "result": "D"
    },
    {
      "date": "2025-09-21",
      "opponent": "Newcastle United",
      "isHome": true,
      "goalsFor": 0,
      "goalsAgainst": 0,
      "result": "D"
    },
    {
      "date": "2025-09-13",
      "opponent": "Brighton",
      "isHome": true,
      "goalsFor": 2,
      "goalsAgainst": 1,
      "result": "W"
    },
    {
      "date": "2025-08-30",
      "opponent": "Tottenham",
      "isHome": false,
      "goalsFor": 1,
      "goalsAgainst": 0,
      "result": "W"
    },
    {
      "date": "2025-08-23",
      "opponent": "Wolves",
      "isHome": true,
      "goalsFor": 1,
      "goalsAgainst": 0,
      "result": "W"
    },
    {
      "date": "2025-08-15",
      "opponent": "Liverpool",
      "isHome": false,
      "goalsFor": 2,
      "goalsAgainst": 4,
      "result": "L"
    },
    {
      "date": "2025-05-25",
      "opponent": "Leicester City",
      "isHome": true,
      "goalsFor": 2,
      "goalsAgainst": 0,
      "result": "W"
    },
    {
      "date": "2025-05-20",
      "opponent": "Manchester City",
      "isHome": false,
      "goalsFor": 1,
      "goalsAgainst": 3,
      "result": "L"
    },
    {
      "date": "2025-05-10",
      "opponent": "Aston Villa",
      "isHome": true,
      "goalsFor": 0,
      "goalsAgainst": 1,
      "result": "L"
    },
    {
      "date": "2025-05-03",
      "opponent": "Arsenal",
      "isHome": false,
      "goalsFor": 2,
      "goalsAgainst": 1,
      "result": "W"
    },
    {
      "date": "2025-04-27",
      "opponent": "Manchester United",
      "isHome": true,
      "goalsFor": 1,
      "goalsAgainst": 1,
      "result": "D"
    },
    {
      "date": "2025-04-19",
      "opponent": "Crystal Palace",
      "isHome": false,
      "goalsFor": 0,
      "goalsAgainst": 0,
      "result": "D"
    },
    {
      "date": "2025-04-14",
      "opponent": "Fulham",
      "isHome": true,
      "goalsFor": 1,
      "goalsAgainst": 0,
      "result": "W"
    },
    {
      "date": "2025-04-05",
      "opponent": "West Ham",
      "isHome": false,
      "goalsFor": 2,
      "goalsAgainst": 2,
      "result": "D"
    },
    {
      "date": "2025-04-02",
      "opponent": "Ipswich Town",
      "isHome": true,
      "goalsFor": 1,
      "goalsAgainst": 2,
      "result": "L"
    },
    {
      "date": "2025-03-15",
      "opponent": "Brentford",
      "isHome": true,
      "goalsFor": 1,
      "goalsAgainst": 2,
      "result": "L"
    },
    {
      "date": "2025-03-09",
      "opponent": "Tottenham",
      "isHome": false,
      "goalsFor": 2,
      "goalsAgainst": 2,
      "result": "D"
    },
    {
      "date": "2025-02-25",
      "opponent": "Brighton",
      "isHome": false,
      "goalsFor": 1,
      "goalsAgainst": 2,
      "result": "L"
    },
    {
      "date": "2025-02-22",
      "opponent": "Wolves",
      "isHome": true,
      "goalsFor": 0,
      "goalsAgainst": 1,
      "result": "L"
    },
    {
      "date": "2025-02-15",
      "opponent": "Southampton",
      "isHome": false,
      "goalsFor": 3,
      "goalsAgainst": 1,
      "result": "W"
    },
    {
      "date": "2025-02-01",
      "opponent": "Liverpool",
      "isHome": true,
      "goalsFor": 0,
      "goalsAgainst": 2,
      "result": "L"
    },
    {
      "date": "2025-01-25",
      "opponent": "Nottingham Forest",
      "isHome": true,
      "goalsFor": 5,
      "goalsAgainst": 0,
      "result": "W"
    },
    {
      "date": "2025-01-18",
      "opponent": "Newcastle United",
      "isHome": false,
      "goalsFor": 4,
      "goalsAgainst": 1,
      "result": "W"
    },
    {
      "date": "2025-01-14",
      "opponent": "Chelsea",
      "isHome": false,
      "goalsFor": 2,
      "goalsAgainst": 2,
      "result": "D"
    },
    {
      "date": "2025-01-04",
      "opponent": "Everton",
      "isHome": true,
      "goalsFor": 1,
      "goalsAgainst": 0,
      "result": "W"
    },
    {
      "date": "2024-12-29",
      "opponent": "Fulham",
      "isHome": false,
      "goalsFor": 2,
      "goalsAgainst": 2,
      "result": "D"
    },
    {
      "date": "2024-12-26",
      "opponent": "Crystal Palace",
      "isHome": true,
      "goalsFor": 0,
      "goalsAgainst": 0,
      "result": "D"
    },
    {
      "date": "2024-12-22",
      "opponent": "Manchester United",
      "isHome": false,
      "goalsFor": 3,
      "goalsAgainst": 0,
      "result": "W"
    },
    {
      "date": "2024-12-16",
      "opponent": "West Ham",
      "isHome": true,
      "goalsFor": 1,
      "goalsAgainst": 1,
      "result": "D"
    },
    {
      "date": "2024-12-08",
      "opponent": "Ipswich Town",
      "isHome": false,
      "goalsFor": 2,
      "goalsAgainst": 1,
      "result": "W"
    },
    {
      "date": "2024-12-05",
      "opponent": "Tottenham",
      "isHome": true,
      "goalsFor": 1,
      "goalsAgainst": 0,
      "result": "W"
    },
    {
      "date": "2024-11-30",
      "opponent": "Wolves",
      "isHome": false,
      "goalsFor": 4,
      "goalsAgainst": 2,
      "result": "W"
    },
    {
      "date": "2024-11-23",
      "opponent": "Brighton",
      "isHome": true,
      "goalsFor": 1,
      "goalsAgainst": 2,
      "result": "L"
    },
    {
      "date": "2024-11-09",
      "opponent": "Brentford",
      "isHome": false,
      "goalsFor": 2,
      "goalsAgainst": 3,
      "result": "L"
    },
    {
      "date": "2024-11-02",
      "opponent": "Manchester City",
      "isHome": true,
      "goalsFor": 2,
      "goalsAgainst": 1,
      "result": "W"
    },
    {
      "date": "2024-10-26",
      "opponent": "Aston Villa",
      "isHome": false,
      "goalsFor": 1,
      "goalsAgainst": 1,
      "result": "D"
    },
    {
      "date": "2024-10-19",
      "opponent": "Arsenal",
      "isHome": true,
      "goalsFor": 2,
      "goalsAgainst": 0,
      "result": "W"
    },
    {
      "date": "2024-10-05",
      "opponent": "Leicester City",
      "isHome": false,
      "goalsFor": 0,
      "goalsAgainst": 1,
      "result": "L"
    },
    {
      "date": "2024-09-30",
      "opponent": "Southampton",
      "isHome": true,
      "goalsFor": 3,
      "goalsAgainst": 1,
      "result": "W"
    },
    {
      "date": "2024-09-21",
      "opponent": "Liverpool",
      "isHome": false,
      "goalsFor": 0,
      "goalsAgainst": 3,
      "result": "L"
    },
    {
      "date": "2024-09-14",
      "opponent": "Chelsea",
      "isHome": true,
      "goalsFor": 0,
      "goalsAgainst": 1,
      "result": "L"
    },
    {
      "date": "2024-08-31",
      "opponent": "Everton",
      "isHome": false,
      "goalsFor": 3,
      "goalsAgainst": 2,
      "result": "W"
    },
    {
      "date": "2024-08-25",
      "opponent": "Newcastle United",
      "isHome": true,
      "goalsFor": 1,
      "goalsAgainst": 1,
      "result": "D"
    },
    {
      "date": "2024-08-17",
      "opponent": "Nottingham Forest",
      "isHome": false,
      "goalsFor": 1,
      "goalsAgainst": 1,
      "result": "D"
    },
    {
      "date": "2024-05-19",
      "opponent": "Chelsea",
      "isHome": false,
      "goalsFor": 1,
      "goalsAgainst": 2,
      "result": "L"
    },
    {
      "date": "2024-05-11",
      "opponent": "Brentford",
      "isHome": true,
      "goalsFor": 1,
      "goalsAgainst": 2,
      "result": "L"
    },
    {
      "date": "2024-05-04",
      "opponent": "Arsenal",
      "isHome": false,
      "goalsFor": 0,
      "goalsAgainst": 3,
      "result": "L"
    },
    {
      "date": "2024-04-28",
      "opponent": "Brighton",
      "isHome": true,
      "goalsFor": 3,
      "goalsAgainst": 0,
      "result": "W"
    },
    {
      "date": "2024-04-24",
      "opponent": "Wolves",
      "isHome": false,
      "goalsFor": 1,
      "goalsAgainst": 0,
      "result": "W"
    },
    {
      "date": "2024-04-21",
      "opponent": "Aston Villa",
      "isHome": false,
      "goalsFor": 1,
      "goalsAgainst": 3,
      "result": "L"
    },
    {
      "date": "2024-04-13",
      "opponent": "Manchester United",
      "isHome": true,
      "goalsFor": 2,
      "goalsAgainst": 2,
      "result": "D"
    },
    {
      "date": "2024-04-06",
      "opponent": "Luton Town",
      "isHome": false,
      "goalsFor": 1,
      "goalsAgainst": 2,
      "result": "L"
    },
    {
      "date": "2024-04-02",
      "opponent": "Crystal Palace",
      "isHome": true,
      "goalsFor": 1,
      "goalsAgainst": 0,
      "result": "W"
    },
    {
      "date": "2024-03-30",
      "opponent": "Everton",
      "isHome": true,
      "goalsFor": 2,
      "goalsAgainst": 1,
      "result": "W"
    },
    {
      "date": "2024-03-13",
      "opponent": "Luton Town",
      "isHome": true,
      "goalsFor": 4,
      "goalsAgainst": 3,
      "result": "W"
    },
    {
      "date": "2024-03-09",
      "opponent": "Sheffield United",
      "isHome": true,
      "goalsFor": 2,
      "goalsAgainst": 2,
      "result": "D"
    },
    {
      "date": "2024-03-03",
      "opponent": "Burnley",
      "isHome": false,
      "goalsFor": 2,
      "goalsAgainst": 0,
      "result": "W"
    },
    {
      "date": "2024-02-24",
      "opponent": "Manchester City",
      "isHome": true,
      "goalsFor": 0,
      "goalsAgainst": 1,
      "result": "L"
    },
    {
      "date": "2024-02-17",
      "opponent": "Newcastle United",
      "isHome": false,
      "goalsFor": 2,
      "goalsAgainst": 2,
      "result": "D"
    },
    {
      "date": "2024-02-10",
      "opponent": "Fulham",
      "isHome": false,
      "goalsFor": 1,
      "goalsAgainst": 3,
      "result": "L"
    },
    {
      "date": "2024-02-04",
      "opponent": "Nottingham Forest",
      "isHome": true,
      "goalsFor": 1,
      "goalsAgainst": 1,
      "result": "D"
    },
    {
      "date": "2024-02-01",
      "opponent": "West Ham",
      "isHome": false,
      "goalsFor": 1,
      "goalsAgainst": 1,
      "result": "D"
    },
    {
      "date": "2024-01-21",
      "opponent": "Liverpool",
      "isHome": true,
      "goalsFor": 0,
      "goalsAgainst": 4,
      "result": "L"
    },
    {
      "date": "2023-12-31",
      "opponent": "Tottenham",
      "isHome": false,
      "goalsFor": 1,
      "goalsAgainst": 3,
      "result": "L"
    },
    {
      "date": "2023-12-26",
      "opponent": "Fulham",
      "isHome": true,
      "goalsFor": 3,
      "goalsAgainst": 0,
      "result": "W"
    },
    {
      "date": "2023-12-23",
      "opponent": "Nottingham Forest",
      "isHome": false,
      "goalsFor": 3,
      "goalsAgainst": 2,
      "result": "W"
    },
    {
      "date": "2023-12-09",
      "opponent": "Manchester United",
      "isHome": false,
      "goalsFor": 3,
      "goalsAgainst": 0,
      "result": "W"
    },
    {
      "date": "2023-12-06",
      "opponent": "Crystal Palace",
      "isHome": false,
      "goalsFor": 2,
      "goalsAgainst": 0,
      "result": "W"
    },
    {
      "date": "2023-12-03",
      "opponent": "Aston Villa",
      "isHome": true,
      "goalsFor": 2,
      "goalsAgainst": 2,
      "result": "D"
    },
    {
      "date": "2023-11-25",
      "opponent": "Sheffield United",
      "isHome": false,
      "goalsFor": 3,
      "goalsAgainst": 1,
      "result": "W"
    },
    {
      "date": "2023-11-11",
      "opponent": "Newcastle United",
      "isHome": true,
      "goalsFor": 2,
      "goalsAgainst": 0,
      "result": "W"
    },
    {
      "date": "2023-11-04",
      "opponent": "Manchester City",
      "isHome": false,
      "goalsFor": 1,
      "goalsAgainst": 6,
      "result": "L"
    },
    {
      "date": "2023-10-28",
      "opponent": "Burnley",
      "isHome": true,
      "goalsFor": 2,
      "goalsAgainst": 1,
      "result": "W"
    },
    {
      "date": "2023-10-21",
      "opponent": "Wolves",
      "isHome": true,
      "goalsFor": 1,
      "goalsAgainst": 2,
      "result": "L"
    },
    {
      "date": "2023-10-07",
      "opponent": "Everton",
      "isHome": false,
      "goalsFor": 0,
      "goalsAgainst": 3,
      "result": "L"
    },
    {
      "date": "2023-09-30",
      "opponent": "Arsenal",
      "isHome": true,
      "goalsFor": 0,
      "goalsAgainst": 4,
      "result": "L"
    },
    {
      "date": "2023-09-24",
      "opponent": "Brighton",
      "isHome": false,
      "goalsFor": 1,
      "goalsAgainst": 3,
      "result": "L"
    },
    {
      "date": "2023-09-17",
      "opponent": "Chelsea",
      "isHome": true,
      "goalsFor": 0,
      "goalsAgainst": 0,
      "result": "D"
    },
    {
      "date": "2023-09-02",
      "opponent": "Brentford",
      "isHome": false,
      "goalsFor": 2,
      "goalsAgainst": 2,
      "result": "D"
    },
    {
      "date": "2023-08-26",
      "opponent": "Tottenham",
      "isHome": true,
      "goalsFor": 0,
      "goalsAgainst": 2,
      "result": "L"
    },
    {
      "date": "2023-08-19",
      "opponent": "Liverpool",
      "isHome": false,
      "goalsFor": 1,
      "goalsAgainst": 3,
      "result": "L"
    },
    {
      "date": "2023-08-12",
      "opponent": "West Ham",
      "isHome": true,
      "goalsFor": 1,
      "goalsAgainst": 1,
      "result": "D"
    },
    {
      "date": "2023-05-28",
      "opponent": "Everton",
      "isHome": false,
      "goalsFor": 0,
      "goalsAgainst": 1,
      "result": "L"
    },
    {
      "date": "2023-05-20",
      "opponent": "Manchester United",
      "isHome": true,
      "goalsFor": 0,
      "goalsAgainst": 1,
      "result": "L"
    },
    {
      "date": "2023-05-13",
      "opponent": "Crystal Palace",
      "isHome": false,
      "goalsFor": 0,
      "goalsAgainst": 2,
      "result": "L"
    },
    {
      "date": "2023-05-06",
      "opponent": "Chelsea",
      "isHome": true,
      "goalsFor": 1,
      "goalsAgainst": 3,
      "result": "L"
    },
    {
      "date": "2023-04-30",
      "opponent": "Leeds United",
      "isHome": true,
      "goalsFor": 4,
      "goalsAgainst": 1,
      "result": "W"
    },
    {
      "date": "2023-04-27",
      "opponent": "Southampton",
      "isHome": false,
      "goalsFor": 1,
      "goalsAgainst": 0,
      "result": "W"
    },
    {
      "date": "2023-04-23",
      "opponent": "West Ham",
      "isHome": true,
      "goalsFor": 0,
      "goalsAgainst": 4,
      "result": "L"
    },
    {
      "date": "2023-04-15",
      "opponent": "Tottenham",
      "isHome": false,
      "goalsFor": 3,
      "goalsAgainst": 2,
      "result": "W"
    },
    {
      "date": "2023-04-08",
      "opponent": "Leicester City",
      "isHome": false,
      "goalsFor": 1,
      "goalsAgainst": 0,
      "result": "W"
    },
    {
      "date": "2023-04-04",
      "opponent": "Brighton",
      "isHome": true,
      "goalsFor": 0,
      "goalsAgainst": 2,
      "result": "L"
    },
    {
      "date": "2023-04-01",
      "opponent": "Fulham",
      "isHome": true,
      "goalsFor": 2,
      "goalsAgainst": 1,
      "result": "W"
    },
    {
      "date": "2023-03-18",
      "opponent": "Aston Villa",
      "isHome": false,
      "goalsFor": 0,
      "goalsAgainst": 3,
      "result": "L"
    },
    {
      "date": "2023-03-11",
      "opponent": "Liverpool",
      "isHome": true,
      "goalsFor": 1,
      "goalsAgainst": 0,
      "result": "W"
    },
    {
      "date": "2023-03-04",
      "opponent": "Arsenal",
      "isHome": false,
      "goalsFor": 2,
      "goalsAgainst": 3,
      "result": "L"
    },
    {
      "date": "2023-02-25",
      "opponent": "Manchester City",
      "isHome": true,
      "goalsFor": 1,
      "goalsAgainst": 4,
      "result": "L"
    },
    {
      "date": "2023-02-18",
      "opponent": "Wolves",
      "isHome": false,
      "goalsFor": 1,
      "goalsAgainst": 0,
      "result": "W"
    },
    {
      "date": "2023-02-11",
      "opponent": "Newcastle United",
      "isHome": true,
      "goalsFor": 1,
      "goalsAgainst": 1,
      "result": "D"
    },
    {
      "date": "2023-02-04",
      "opponent": "Brighton",
      "isHome": false,
      "goalsFor": 0,
      "goalsAgainst": 1,
      "result": "L"
    },
    {
      "date": "2023-01-21",
      "opponent": "Nottingham Forest",
      "isHome": true,
      "goalsFor": 1,
      "goalsAgainst": 1,
      "result": "D"
    },
    {
      "date": "2023-01-14",
      "opponent": "Brentford",
      "isHome": false,
      "goalsFor": 0,
      "goalsAgainst": 2,
      "result": "L"
    },
    {
      "date": "2023-01-03",
      "opponent": "Manchester United",
      "isHome": false,
      "goalsFor": 0,
      "goalsAgainst": 3,
      "result": "L"
    },
    {
      "date": "2022-12-31",
      "opponent": "Crystal Palace",
      "isHome": true,
      "goalsFor": 0,
      "goalsAgainst": 2,
      "result": "L"
    },
    {
      "date": "2022-12-27",
      "opponent": "Chelsea",
      "isHome": false,
      "goalsFor": 0,
      "goalsAgainst": 2,
      "result": "L"
    },
    {
      "date": "2022-11-12",
      "opponent": "Everton",
      "isHome": true,
      "goalsFor": 3,
      "goalsAgainst": 0,
      "result": "W"
    },
    {
      "date": "2022-11-05",
      "opponent": "Leeds United",
      "isHome": false,
      "goalsFor": 3,
      "goalsAgainst": 4,
      "result": "L"
    },
    {
      "date": "2022-10-29",
      "opponent": "Tottenham",
      "isHome": true,
      "goalsFor": 2,
      "goalsAgainst": 3,
      "result": "L"
    },
    {
      "date": "2022-10-24",
      "opponent": "West Ham",
      "isHome": false,
      "goalsFor": 0,
      "goalsAgainst": 2,
      "result": "L"
    },
    {
      "date": "2022-10-19",
      "opponent": "Southampton",
      "isHome": true,
      "goalsFor": 0,
      "goalsAgainst": 1,
      "result": "L"
    },
    {
      "date": "2022-10-15",
      "opponent": "Fulham",
      "isHome": false,
      "goalsFor": 2,
      "goalsAgainst": 2,
      "result": "D"
    },
    {
      "date": "2022-10-08",
      "opponent": "Leicester City",
      "isHome": true,
      "goalsFor": 2,
      "goalsAgainst": 1,
      "result": "W"
    },
    {
      "date": "2022-10-01",
      "opponent": "Brentford",
      "isHome": true,
      "goalsFor": 0,
      "goalsAgainst": 0,
      "result": "D"
    },
    {
      "date": "2022-09-17",
      "opponent": "Newcastle United",
      "isHome": false,
      "goalsFor": 1,
      "goalsAgainst": 1,
      "result": "D"
    },
    {
      "date": "2022-09-03",
      "opponent": "Nottingham Forest",
      "isHome": false,
      "goalsFor": 3,
      "goalsAgainst": 2,
      "result": "W"
    },
    {
      "date": "2022-08-31",
      "opponent": "Wolves",
      "isHome": true,
      "goalsFor": 0,
      "goalsAgainst": 0,
      "result": "D"
    },
    {
      "date": "2022-08-27",
      "opponent": "Liverpool",
      "isHome": false,
      "goalsFor": 0,
      "goalsAgainst": 9,
      "result": "L"
    },
    {
      "date": "2022-08-20",
      "opponent": "Arsenal",
      "isHome": true,
      "goalsFor": 0,
      "goalsAgainst": 3,
      "result": "L"
    },
    {
      "date": "2022-08-13",
      "opponent": "Manchester City",
      "isHome": false,
      "goalsFor": 0,
      "goalsAgainst": 4,
      "result": "L"
    },
    {
      "date": "2022-08-06",
      "opponent": "Aston Villa",
      "isHome": true,
      "goalsFor": 2,
      "goalsAgainst": 0,
      "result": "W"
    }
  ],
  "stats": {
    "played": 131,
    "wins": 44,
    "draws": 33,
    "losses": 54,
    "goalsFor": 175,
    "goalsAgainst": 213
  }
}